zealium/__init__.py
zealium/core.py
zealium/human.py
zealium/injections/audio_oscillator_patch.js
zealium/injections/canvas_noise.js
zealium/injections/intl_datetime_patch.js
zealium/injections/mock_audio_fingerprint.js
zealium/injections/mock_chrome_runtime.js
zealium/injections/mock_media_devices.js
zealium/injections/mock_navigator_connection.js
zealium/injections/mock_navigator_plugins_and_mimetypes.js
zealium/injections/mock_webrtc.js
zealium/injections/navigator_properties.js
zealium/injections/override_function_toString.js
zealium/injections/permissions_query_patch.js
zealium/injections/rtc_peerconnection_patch.js
zealium/injections/screen_properties.js
zealium/injections/spoof_canvas_fingerprint.js
zealium/injections/spoof_webgl_precision.js
zealium/injections/webgl_spoof.js
zealium/stealth.py
zealium-0.1.7.post2.dist-info/LICENSE
zealium-0.1.7.post2.dist-info/METADATA
zealium-0.1.7.post2.dist-info/WHEEL
zealium-0.1.7.post2.dist-info/RECORD
