Metadata-Version: 2.3
Name: zealium
Version: 0.1.7.post2
Summary: A stealthy Chromium remote-control tool using DevTools Protocol with dynamic JS injection to evade bot detection.
License: MIT
Author: Renks
Requires-Python: >=3.11
Classifier: License :: OSI Approved :: MIT License
Classifier: Programming Language :: Python :: 3
Classifier: Programming Language :: Python :: 3.11
Classifier: Programming Language :: Python :: 3.12
Classifier: Programming Language :: Python :: 3.13
Requires-Dist: psutil (>=7.0.0,<8.0.0)
Requires-Dist: pychrome (>=0.2.4,<0.3.0)
Requires-Dist: websocket-client (>=1.8.0,<2.0.0)
